{
	"sold": [
		{
			"name": "Botruc",
			"desc": "Petite créature d'une vingtaine de centimètres ayant un aspect végétal et deux longs doigts pointus à chaque main. - Peut crocheter des serrures -",
			"price": 400
			"owner": "nDragonneau"
			"end": 0065105984085529
		},
	],
	"pending": [
		{
			"name": "Botruc",
			"desc": "Petite créature d'une vingtaine de centimètres ayant un aspect végétal et deux longs doigts pointus à chaque main. - Peut crocheter des serrures -",
			"price": 480
			"leader": "aCarat"
			"end": 0065105984085529
		}
	],
	"bought": [
		
	]
}